[
  {
    "name": "Poland",
    "value1": "3",
    "value2": "2",
    "country": "Poland"
  },
  {
    "name": "Hungary",
    "value1": "3",
    "value2": "2",
    "country": "Hungary"
  },
  {
    "name": "Spain",
    "value1": "3",
    "value2": "2",
    "country": "Spain"
  },
  {
    "name": "Romania",
    "value1": "3",
    "value2": "2",
    "country": "Romania"
  },
  {
    "name": "Italy",
    "value1": "3",
    "value2": "2",
    "country": "Italy"
  },
  {
    "name": "Egypt",
    "value1": "3",
    "value2": "2",
    "country": "Egypt"
  }
]